cghq_common/__init__.py
cghq_common/compat.py
cghq_common/config.py
cghq_common/constants.py
cghq_common/utils.py
cghq_common-0.0.2.dist-info/DESCRIPTION.rst
cghq_common-0.0.2.dist-info/METADATA
cghq_common-0.0.2.dist-info/metadata.json
cghq_common-0.0.2.dist-info/RECORD
cghq_common-0.0.2.dist-info/top_level.txt
cghq_common-0.0.2.dist-info/WHEEL
