Metadata-Version: 2.0
Name: cghq-common
Version: 0.0.2
Summary: Central package for utility functions.
Home-page: https://github.com/Clinical-Genomics/cghq-common
Author: Robin Andeer
Author-email: robin.andeer@scilifelab.se
License: MIT
Keywords: c,g,h,q, ,d,e,v,e,l,o,p,m,e,n,t
Platform: UNKNOWN
Classifier: Development Status :: 3 - Alpha
Classifier: Intended Audience :: Developers
Classifier: Topic :: Software Development
Classifier: License :: OSI Approved :: MIT License
Classifier: Programming Language :: Python :: 2
Classifier: Programming Language :: Python :: 2.7
Classifier: Environment :: Console
Requires-Dist: pymongo
Requires-Dist: nameko (==2.1.2)
Requires-Dist: path.py (==7.6)
Requires-Dist: setuptools
